README.md
setup.py
allib/__init__.py
allib/data.py
allib/di.py
allib/diff.py
allib/flask.py
allib/logging.py
allib/reflection.py
allib/sqla.py
allib/subprocess.py
allib/testing.py
allib.egg-info/PKG-INFO
allib.egg-info/SOURCES.txt
allib.egg-info/dependency_links.txt
allib.egg-info/top_level.txt
allib/options/__init__.py
allib/options/argparser.py
allib/options/config.py
allib/options/spec.py