Metadata-Version: 1.1
Name: allib
Version: 1.2
Summary: Personal library of useful stuff.
Home-page: https://github.com/anlutro/allib.py
Author: Andreas Lutro
Author-email: anlutro@gmail.com
License: MIT
Keywords: personal,library,utils
Platform: UNKNOWN
Classifier: Development Status :: 4 - Beta
Classifier: Intended Audience :: Developers
Classifier: Operating System :: POSIX
Classifier: Programming Language :: Python
Classifier: Programming Language :: Python :: 3.4
Classifier: Programming Language :: Python :: 3.5
Classifier: Programming Language :: Python :: 3.6
Classifier: Programming Language :: Python :: 3.7
